{ "columns":0,
 "grid":
    {
     "height":1,
     "orientation":"orthogonal",
     "width":1
    },
 "margin":0,
 "name":"images",
 "spacing":0,
 "tilecount":15,
 "tiledversion":"1.7.2",
 "tileheight":136,
 "tiles":[
        {
         "id":0,
         "image":"images\/apple.png",
         "imageheight":32,
         "imagewidth":32
        }, 
        {
         "id":1,
         "image":"images\/ball.png",
         "imageheight":32,
         "imagewidth":32
        }, 
        {
         "id":2,
         "image":"images\/banana.png",
         "imageheight":32,
         "imagewidth":32
        }, 
        {
         "id":3,
         "image":"images\/box.png",
         "imageheight":64,
         "imagewidth":64
        }, 
        {
         "id":4,
         "image":"images\/grape.png",
         "imageheight":32,
         "imagewidth":32
        }, 
        {
         "id":5,
         "image":"images\/hole.png",
         "imageheight":32,
         "imagewidth":32
        }, 
        {
         "id":6,
         "image":"images\/orange.png",
         "imageheight":32,
         "imagewidth":32
        }, 
        {
         "id":7,
         "image":"images\/pineapple.png",
         "imageheight":32,
         "imagewidth":32
        }, 
        {
         "id":8,
         "image":"images\/rock.png",
         "imageheight":98,
         "imagewidth":98,
         "objectgroup":
            {
             "draworder":"index",
             "id":2,
             "name":"",
             "objects":[
                    {
                     "ellipse":true,
                     "height":40,
                     "id":1,
                     "name":"",
                     "rotation":0,
                     "type":"",
                     "visible":true,
                     "width":80,
                     "x":8.68361,
                     "y":47.3672
                    }],
             "opacity":1,
             "type":"objectgroup",
             "visible":true,
             "x":0,
             "y":0
            }
        }, 
        {
         "id":9,
         "image":"images\/strawberry.png",
         "imageheight":32,
         "imagewidth":32
        }, 
        {
         "id":10,
         "image":"images\/tree_short.png",
         "imageheight":107,
         "imagewidth":98,
         "objectgroup":
            {
             "draworder":"index",
             "id":2,
             "name":"",
             "objects":[
                    {
                     "ellipse":true,
                     "height":37.1881,
                     "id":1,
                     "name":"",
                     "rotation":0,
                     "type":"",
                     "visible":true,
                     "width":64.5033,
                     "x":16.784,
                     "y":58.2505
                    }],
             "opacity":1,
             "type":"objectgroup",
             "visible":true,
             "x":0,
             "y":0
            }
        }, 
        {
         "id":11,
         "image":"images\/tree_tall.png",
         "imageheight":136,
         "imagewidth":100,
         "objectgroup":
            {
             "draworder":"index",
             "id":2,
             "name":"",
             "objects":[
                    {
                     "ellipse":true,
                     "height":33.239,
                     "id":1,
                     "name":"",
                     "rotation":0,
                     "type":"",
                     "visible":true,
                     "width":64.1742,
                     "x":19.0877,
                     "y":92.8058
                    }],
             "opacity":1,
             "type":"objectgroup",
             "visible":true,
             "x":0,
             "y":0
            }
        }, 
        {
         "id":12,
         "image":"images\/tree_ugly.png",
         "imageheight":115,
         "imagewidth":101,
         "objectgroup":
            {
             "draworder":"index",
             "id":2,
             "name":"",
             "objects":[
                    {
                     "ellipse":true,
                     "height":40,
                     "id":1,
                     "name":"",
                     "rotation":0,
                     "type":"",
                     "visible":true,
                     "width":80,
                     "x":10.8603,
                     "y":56.2759
                    }],
             "opacity":1,
             "type":"objectgroup",
             "visible":true,
             "x":0,
             "y":0
            }
        }, 
        {
         "id":13,
         "image":"images\/watermelon.png",
         "imageheight":32,
         "imagewidth":32
        }, 
        {
         "id":14,
         "image":"images\/enemy.png",
         "imageheight":77,
         "imagewidth":99
        }],
 "tilewidth":101,
 "type":"tileset",
 "version":"1.6"
}